{
  "Users": [
    {
      "Date": "17/10/20",
      "Arrived travellers": "10830",
      "Total users provided consent": "3934",
      "Travellers arrived and provided consent": "2527",
      "Travellers arrived and completed setup": "2342"
    },
    {
      "Date": "16/10/20",
      "Arrived travellers": "10279",
      "Total users provided consent": "3830",
      "Travellers arrived and provided consent": "2374",
      "Travellers arrived and completed setup": "2207"
    },
    {
      "Date": "15/10/20",
      "Arrived travellers": "9753",
      "Total users provided consent": "3643",
      "Travellers arrived and provided consent": "2233",
      "Travellers arrived and completed setup": "2072"
    },
    {
      "Date": "14/10/20",
      "Arrived travellers": "9167",
      "Total users provided consent": "3463",
      "Travellers arrived and provided consent": "2087",
      "Travellers arrived and completed setup": "1935"
    },
    {
      "Date": "13/10/20",
      "Arrived travellers": "8649",
      "Total users provided consent": "3370",
      "Travellers arrived and provided consent": "2000",
      "Travellers arrived and completed setup": "1853"
    },
    {
      "Date": "12/10/20",
      "Arrived travellers": "8501",
      "Total users provided consent": "3334",
      "Travellers arrived and provided consent": "1975",
      "Travellers arrived and completed setup": "1831"
    },
    {
      "Date": "11/10/20",
      "Arrived travellers": "7731",
      "Total users provided consent": "3158",
      "Travellers arrived and provided consent": "1788",
      "Travellers arrived and completed setup": "1656"
    },
    {
      "Date": "10/10/20",
      "Arrived travellers": "6586",
      "Total users provided consent": "2864",
      "Travellers arrived and provided consent": "1556",
      "Travellers arrived and completed setup": "1431" 
    },
    {
      "Date": "09/10/20",
      "Arrived travellers": "6056",
      "Total users provided consent": "2780",
      "Travellers arrived and provided consent": "1416",
      "Travellers arrived and completed setup": "1307"
    }    
  ]
}